pandas_to_sql/__init__.py
pandas_to_sql/conventions/__init__.py
pandas_to_sql/conventions/groupby_conventions.py
pandas_to_sql/engine/__init__.py
pandas_to_sql/engine/grouped_table.py
pandas_to_sql/engine/table.py
pandas_to_sql/engine/columns/__init__.py
pandas_to_sql/engine/columns/bool_column.py
pandas_to_sql/engine/columns/column.py
pandas_to_sql/engine/columns/common.py
pandas_to_sql/engine/columns/numeric_columns.py
pandas_to_sql/engine/columns/str_column.py
pandas_to_sql/engine/columns/timestamp_column.py
pandas_to_sql/testing/__init__.py
pandas_to_sql/testing/conftest.py
pandas_to_sql/testing/utils/__init__.py
pandas_to_sql/testing/utils/asserters.py
pandas_to_sql/testing/utils/fake_data_creation.py
pandas_to_sql/utils/__init__.py
pandas_to_sql/utils/helpers.py
pandas_to_sql/utils/pandas_dataframe_intercepter.py
pandas_to_sql/utils/pandas_interceptor.py
pandas_to_sql-0.0.546.dist-info/LICENSE
pandas_to_sql-0.0.546.dist-info/METADATA
pandas_to_sql-0.0.546.dist-info/WHEEL
pandas_to_sql-0.0.546.dist-info/top_level.txt
pandas_to_sql-0.0.546.dist-info/RECORD
