Metadata-Version: 2.1
Name: pandas-to-sql
Version: 0.0.546
Summary: Convert pandas dataframe manipulations to sql query string
Home-page: https://github.com/AmirPupko/pandas-to-sql
Author: Amir
Author-email: amirpupko@gmail.com
License: UNKNOWN
Platform: UNKNOWN
Classifier: Programming Language :: Python :: 3
Classifier: License :: OSI Approved :: MIT License
Classifier: Operating System :: OS Independent
Requires-Python: >=3.6
